{
  "generatedAt": "2026-04-29T11:01:10.174Z",
  "categories": [
    {
      "key": "rental",
      "label": "임대",
      "noticeCount": 50,
      "newNoticeCount": 5,
      "updatedNoticeCount": 0,
      "noticesUrl": "/rental/notices.json",
      "metadataUrl": "/rental/metadata.json"
    },
    {
      "key": "sale",
      "label": "분양",
      "noticeCount": 7,
      "newNoticeCount": 0,
      "updatedNoticeCount": 0,
      "noticesUrl": "/sale/notices.json",
      "metadataUrl": "/sale/metadata.json"
    },
    {
      "key": "land",
      "label": "토지",
      "noticeCount": 36,
      "newNoticeCount": 0,
      "updatedNoticeCount": 0,
      "noticesUrl": "/land/notices.json",
      "metadataUrl": "/land/metadata.json"
    }
  ]
}
